lumiML/__init__.py
lumiml-0.1.0.dist-info/METADATA
lumiml-0.1.0.dist-info/WHEEL
lumiml-0.1.0.dist-info/top_level.txt
lumiml-0.1.0.dist-info/RECORD
