Metadata-Version: 2.4
Name: lumiML
Version: 0.1.0
Summary: A data preprocessing and cleaning toolkit for machine learning. Still under active development.
Home-page: https://github.com/Cod4L/lumiML
Author: Moon
Classifier: Development Status :: 3 - Alpha
Classifier: Programming Language :: Python :: 3
Classifier: License :: OSI Approved :: MIT License
Classifier: Operating System :: OS Independent
Classifier: Intended Audience :: Developers
Classifier: Topic :: Scientific/Engineering :: Information Analysis
Requires-Python: >=3.7
Requires-Dist: pandas
Requires-Dist: numpy
Requires-Dist: scikit-learn
Requires-Dist: tensorflow
Requires-Dist: opencv-python
Requires-Dist: seaborn
Requires-Dist: matplotlib
Requires-Dist: joblib
Requires-Dist: scipy
Dynamic: author
Dynamic: classifier
Dynamic: description
Dynamic: description-content-type
Dynamic: home-page
Dynamic: requires-dist
Dynamic: requires-python
Dynamic: summary
